{
  "invoice_date": "7/19/2024",
  "invoice_id": "539265",
  "due_date": "8/19/2024",
  "ship_to_address": "500 South 59th Ave. West\nDock 6\nDuluth, MN 55807",
  "receiver_name": "Camp Cider LLC DBA Wild State Cider",
  "net_amount": "2,590.31",
  "ship_to_name": "Camp Cider LLC DBA Wild State Cider",
  "receiver_address": "500 South 59th Ave. West\nDuluth\n, \nMN \n55807",
  "payment_terms": "Net 30 Days",
  "supplier_phone": "614-875-9010",
  "supplier_address": "2050 Hardy Parkway\nColumbus, OH 43123",
  "total_amount": "2,590.31",
  "invoice_type": "",
  "purchase_order": "July Beer Day",
  "supplier_name": "MAMMOTH\nLABELS & PACKAGING",
  "line_items": [
    {
      "line_item/quantity": "26,700",
      "line_item/unit_price": "81.00000",
      "line_item/amount": "2,162.70",
      "line_item/description": "Birdie Tea + Lemonade\n433170 Birdie Tea + Lemonade"
    },
    {
      "line_item/description": "Your PO: July Beer Day"
    },
    {
      "line_item/quantity": "2,600",
      "line_item/description": "Hazy Apple Pie\n433171 Hazy Apple Pie\nExtra costs :",
      "line_item/unit_price": "81.00000",
      "line_item/amount": "210.60"
    },
    {
      "line_item/quantity": "1",
      "line_item/description": "Freight Label 71",
      "line_item/amount": "217.01"
    }
  ],
  "fieldsConfidence": [
    {
      "field": "invoice_date",
      "confidence": 0.9846675395965576
    },
    {
      "field": "invoice_id",
      "confidence": 0.9792669415473938
    },
    {
      "field": "due_date",
      "confidence": 0.9661000370979309
    },
    {
      "field": "ship_to_address",
      "confidence": 0.9366819262504578
    },
    {
      "field": "receiver_name",
      "confidence": 0.8434152603149414
    },
    {
      "field": "net_amount",
      "confidence": 0.804270327091217
    },
    {
      "field": "ship_to_name",
      "confidence": 0.7839861512184143
    },
    {
      "field": "receiver_address",
      "confidence": 0.6978092789649963
    },
    {
      "field": "payment_terms",
      "confidence": 0.6719489693641663
    },
    {
      "field": "supplier_phone",
      "confidence": 0.6207324862480164
    },
    {
      "field": "supplier_address",
      "confidence": 0.5634039044380188
    },
    {
      "field": "total_amount",
      "confidence": 0.5524168014526367
    },
    {
      "field": "invoice_type",
      "confidence": 0.4330684244632721
    },
    {
      "field": "purchase_order",
      "confidence": 0.29414984583854675
    },
    {
      "field": "supplier_name",
      "confidence": 0.16035321354866028
    },
    {
      "field": "line_item.0.line_item/quantity",
      "confidence": 0.9764688014984131
    },
    {
      "field": "line_item.0.line_item/unit_price",
      "confidence": 0.9307737946510315
    },
    {
      "field": "line_item.0.line_item/amount",
      "confidence": 0.8878265619277954
    },
    {
      "field": "line_item.0.line_item/description",
      "confidence": 0.4499339759349823
    },
    {
      "field": "line_item.1.line_item/description",
      "confidence": 0.5735731720924377
    },
    {
      "field": "line_item.2.line_item/quantity",
      "confidence": 0.953861653804779
    },
    {
      "field": "line_item.2.line_item/description",
      "confidence": 0.4518374502658844
    },
    {
      "field": "line_item.2.line_item/unit_price",
      "confidence": 0.923659086227417
    },
    {
      "field": "line_item.2.line_item/amount",
      "confidence": 0.8677619099617004
    },
    {
      "field": "line_item.3.line_item/quantity",
      "confidence": 0.5112661123275757
    },
    {
      "field": "line_item.3.line_item/description",
      "confidence": 0.5504040122032166
    },
    {
      "field": "line_item.3.line_item/amount",
      "confidence": 0.7644807696342468
    }
  ],
  "receivedAt": "2024-12-18T02:18:39.723Z",
  "processedAt": "2024-12-18T02:18:39.723Z",
  "from": "",
  "messageId": "",
  "snippet": "",
  "subject": "",
  "emailDocId": ""
}