{
  "due_date": "05/10/2024",
  "net_amount": "-117.58",
  "total_amount": "2,273.93",
  "invoice_id": "INV-30515319",
  "invoice_date": "04/10/2024",
  "supplier_address": "1301 Edison Hwy, Suite A-2, Baltimore MD,\n21213, United States",
  "ship_to_address": "1001 Canal Blvd, #C-2\nRichmond CA 94804\nUnited States",
  "remit_to_name": "Wildpack Holdings U.S. Inc.",
  "payment_terms": "30 Days from invoice date.",
  "ship_to_name": "East Brother Beer Company, East Brother - Deliveries",
  "currency": "$",
  "supplier_phone": "+1 833-999-7225",
  "supplier_name": "wildpack",
  "invoice_type": "",
  "receiver_address": "mond CA 94804\nUnited States",
  "line_items": [
    {
      "line_item/unit_price": "0.465000",
      "line_item/amount": "2,351.51",
      "line_item/description": "East Brother - Bo Pils - 19.2oz Standard Sleeved Can (Ball; Glossy;\nBPANI)",
      "line_item/quantity": "5,057.00",
      "line_item/unit": "Unit"
    },
    {
      "line_item/quantity": "1.00",
      "line_item/unit": "Unit",
      "line_item/unit_price": "0.000000",
      "line_item/amount": "0.00"
    },
    {
      "line_item/description": "One-Way Wood Dunnage",
      "line_item/quantity": "2.00",
      "line_item/unit": "Unit",
      "line_item/unit_price": "0.000000",
      "line_item/amount": "0.00"
    },
    {
      "line_item/description": "[SHIP-CARDBOARD] Cardboard Pallet Wrap Sheets",
      "line_item/quantity": "4.00",
      "line_item/unit": "Unit",
      "line_item/unit_price": "10.000000",
      "line_item/amount": "40.00"
    },
    {
      "line_item/description": "Two cardboard wrap sheets required for each finished pallet."
    },
    {
      "line_item/description": "IBA Affiliate Discount - Sleeved Cans 5% Off",
      "line_item/quantity": "1.00",
      "line_item/unit": "Unit",
      "line_item/unit_price": "117.575500",
      "line_item/amount": "117.58"
    }
  ],
  "fieldsConfidence": [
    {
      "field": "due_date",
      "confidence": 0.9747153520584106
    },
    {
      "field": "net_amount",
      "confidence": 0.964031457901001
    },
    {
      "field": "total_amount",
      "confidence": 0.9641350507736206
    },
    {
      "field": "invoice_id",
      "confidence": 0.924485981464386
    },
    {
      "field": "invoice_date",
      "confidence": 0.8972936868667603
    },
    {
      "field": "supplier_address",
      "confidence": 0.8023492693901062
    },
    {
      "field": "ship_to_address",
      "confidence": 0.7982674241065979
    },
    {
      "field": "remit_to_name",
      "confidence": 0.760860025882721
    },
    {
      "field": "payment_terms",
      "confidence": 0.7510101795196533
    },
    {
      "field": "ship_to_name",
      "confidence": 0.7190436720848083
    },
    {
      "field": "currency",
      "confidence": 0.6976599097251892
    },
    {
      "field": "supplier_phone",
      "confidence": 0.5687136054039001
    },
    {
      "field": "supplier_name",
      "confidence": 0.5047537684440613
    },
    {
      "field": "invoice_type",
      "confidence": 0.28659138083457947
    },
    {
      "field": "receiver_address",
      "confidence": 0.0006259676301851869
    },
    {
      "field": "line_item.0.line_item/unit_price",
      "confidence": 0.9180140495300293
    },
    {
      "field": "line_item.0.line_item/amount",
      "confidence": 0.862335205078125
    },
    {
      "field": "line_item.0.line_item/description",
      "confidence": 0.5852251648902893
    },
    {
      "field": "line_item.0.line_item/quantity",
      "confidence": 0.9404112100601196
    },
    {
      "field": "line_item.0.line_item/unit",
      "confidence": 0.5436640381813049
    },
    {
      "field": "line_item.1.line_item/quantity",
      "confidence": 0.9212563633918762
    },
    {
      "field": "line_item.1.line_item/unit",
      "confidence": 0.4651019275188446
    },
    {
      "field": "line_item.1.line_item/unit_price",
      "confidence": 0.9381592273712158
    },
    {
      "field": "line_item.1.line_item/amount",
      "confidence": 0.7126675248146057
    },
    {
      "field": "line_item.2.line_item/description",
      "confidence": 0.47642505168914795
    },
    {
      "field": "line_item.2.line_item/quantity",
      "confidence": 0.9092546701431274
    },
    {
      "field": "line_item.2.line_item/unit",
      "confidence": 0.5526365637779236
    },
    {
      "field": "line_item.2.line_item/unit_price",
      "confidence": 0.9278760552406311
    },
    {
      "field": "line_item.2.line_item/amount",
      "confidence": 0.7441635131835938
    },
    {
      "field": "line_item.3.line_item/description",
      "confidence": 0.5258031487464905
    },
    {
      "field": "line_item.3.line_item/quantity",
      "confidence": 0.9006166458129883
    },
    {
      "field": "line_item.3.line_item/unit",
      "confidence": 0.6167010068893433
    },
    {
      "field": "line_item.3.line_item/unit_price",
      "confidence": 0.9146894812583923
    },
    {
      "field": "line_item.3.line_item/amount",
      "confidence": 0.7918606996536255
    },
    {
      "field": "line_item.4.line_item/description",
      "confidence": 0.4985167682170868
    },
    {
      "field": "line_item.5.line_item/description",
      "confidence": 0.5888313055038452
    },
    {
      "field": "line_item.5.line_item/quantity",
      "confidence": 0.9529209733009338
    },
    {
      "field": "line_item.5.line_item/unit",
      "confidence": 0.19105684757232666
    },
    {
      "field": "line_item.5.line_item/unit_price",
      "confidence": 0.880257785320282
    },
    {
      "field": "line_item.5.line_item/amount",
      "confidence": 0.8092660903930664
    }
  ],
  "receivedAt": "2024-12-18T02:18:39.499Z",
  "processedAt": "2024-12-18T02:18:39.499Z",
  "from": "",
  "messageId": "",
  "snippet": "",
  "subject": "",
  "emailDocId": ""
}